MANIFEST.in
README.rst
setup.py
file_or_name/__init__.py
file_or_name/file_or_name.py
file_or_name/utils.py
file_or_name.egg-info/PKG-INFO
file_or_name.egg-info/SOURCES.txt
file_or_name.egg-info/dependency_links.txt
file_or_name.egg-info/entry_points.txt
file_or_name.egg-info/requires.txt
file_or_name.egg-info/top_level.txt