Metadata-Version: 2.1
Name: file-or-name
Version: 1.1.6
Summary: File Or Name
Home-page: https://github.com/blester125/file-or-name
Author: blester125
Author-email: blester125@gmail.com
License: MIT
Download-URL: https://github.com/blester125/file-or-name/archive/1.1.6.tar.gz
Platform: UNKNOWN
Classifier: Development Status :: 3 - Alpha
Classifier: License :: OSI Approved :: MIT License
Classifier: Programming Language :: Python :: 3 :: Only
Classifier: Topic :: Scientific/Engineering
Classifier: Natural Language :: English
Classifier: Intended Audience :: Developers
Classifier: Environment :: Console
Classifier: Intended Audience :: Science/Research
Requires-Python: >=3.6
Provides-Extra: test
